textnotes/__init__.py
textnotes/__main__.py
textnotes/cli.py
textnotes/processor.py
textnotes/utils.py
textnotes-0.1.1.dist-info/licenses/LICENSE.txt
textnotes-0.1.1.dist-info/METADATA
textnotes-0.1.1.dist-info/WHEEL
textnotes-0.1.1.dist-info/entry_points.txt
textnotes-0.1.1.dist-info/top_level.txt
textnotes-0.1.1.dist-info/RECORD
