Metadata-Version: 2.4
Name: textnotes
Version: 0.1.1
Summary: Convert plain text into summaries, notes, flashcards, JSON, topic groups.
Author: AnushaCoder
Author-email: anushacoder02@gmail.com
License: MIT
Project-URL: Source Repository, https://github.com/anushacoder02/Textnotes/
Requires-Python: >=3.7
License-File: LICENSE.txt
Dynamic: author
Dynamic: author-email
Dynamic: description
Dynamic: description-content-type
Dynamic: license
Dynamic: license-file
Dynamic: project-url
Dynamic: requires-python
Dynamic: summary
